doclayer_cli/__init__.py
doclayer_cli/__main__.py
doclayer_cli/agent.py
doclayer_cli/api_client.py
doclayer_cli/auth.py
doclayer_cli/billing.py
doclayer_cli/cli.py
doclayer_cli/config.py
doclayer_cli/config_cli.py
doclayer_cli/document.py
doclayer_cli/ingest.py
doclayer_cli/local_cli.py
doclayer_cli/model.py
doclayer_cli/pgvector_probe.py
doclayer_cli/project.py
doclayer_cli/search.py
doclayer_cli/state.py
doclayer_cli/status.py
doclayer_cli/template_cli.py
doclayer_cli/version.py
doclayer_cli/workflow.py
doclayer_cli-1.2.1.dist-info/licenses/LICENSE
tests/conftest.py
tests/test_bulk_ingest_smoke.py
tests/test_status_grounding.py
tests/test_upload_state.py
doclayer_cli-1.2.1.dist-info/METADATA
doclayer_cli-1.2.1.dist-info/WHEEL
doclayer_cli-1.2.1.dist-info/entry_points.txt
doclayer_cli-1.2.1.dist-info/top_level.txt
doclayer_cli-1.2.1.dist-info/RECORD
