Metadata-Version: 2.4
Name: doclayer-cli
Version: 1.2.1
Summary: Doclayer Command-Line Interface - Document Intelligence Platform CLI
Author-email: Doclayer <support@doclayer.ai>
Maintainer-email: Doclayer <support@doclayer.ai>
License-Expression: LicenseRef-Proprietary
Project-URL: Homepage, https://doclayer.ai
Project-URL: Documentation, https://docs.doclayer.ai/cli
Project-URL: Repository, https://github.com/okc0mputex/Doclayer
Project-URL: Issues, https://github.com/okc0mputex/Doclayer/issues
Project-URL: Changelog, https://github.com/okc0mputex/Doclayer/blob/main/docs/cli/DOCLAYER_CLI_SDK_SPECIFICATION.md
Keywords: doclayer,cli,document,ai,llm,document-processing
Classifier: Development Status :: 4 - Beta
Classifier: Intended Audience :: Developers
Classifier: Programming Language :: Python :: 3
Classifier: Programming Language :: Python :: 3.11
Classifier: Programming Language :: Python :: 3.12
Classifier: Programming Language :: Python :: 3.13
Classifier: Topic :: Software Development :: Libraries :: Python Modules
Classifier: Topic :: Text Processing :: Markup
Classifier: Topic :: Utilities
Requires-Python: >=3.11
License-File: LICENSE
Requires-Dist: typer[all]>=0.12.3
Requires-Dist: httpx>=0.27.0
Requires-Dist: pydantic>=2.7.0
Requires-Dist: rich>=13.0.0
Requires-Dist: keyring>=25.0.0
Requires-Dist: pyyaml>=6.0.0
Provides-Extra: dev
Requires-Dist: pytest>=8.3.0; extra == "dev"
Requires-Dist: respx>=0.21.1; extra == "dev"
Requires-Dist: psycopg[binary]>=3.1.18; extra == "dev"
Dynamic: license-file
